mcp_asr/__init__.py
mcp_asr/asr_api.py
mcp_asr/server.py
asr_mcp_server-0.1.1.dist-info/METADATA
asr_mcp_server-0.1.1.dist-info/WHEEL
asr_mcp_server-0.1.1.dist-info/entry_points.txt
asr_mcp_server-0.1.1.dist-info/top_level.txt
asr_mcp_server-0.1.1.dist-info/RECORD
