Metadata-Version: 2.4
Name: asr-mcp-server
Version: 0.1.1
Summary: Add your description here
Requires-Python: >=3.11
Requires-Dist: mcp[cli]>=1.6.0
Requires-Dist: requests>=2.32.3
Requires-Dist: uuid>=1.30
